README
setup.py
doc/Makefile
doc/conf.py
doc/index.rst
doc/_build/doctrees/environment.pickle
doc/_build/doctrees/index.doctree
doc/_build/html/genindex.html
doc/_build/html/index.html
doc/_build/html/modindex.html
doc/_build/html/objects.inv
doc/_build/html/search.html
doc/_build/html/searchindex.js
doc/_build/html/_sources/index.txt
doc/_build/html/_static/contents.png
doc/_build/html/_static/default.css
doc/_build/html/_static/doctools.js
doc/_build/html/_static/file.png
doc/_build/html/_static/jquery.js
doc/_build/html/_static/minus.png
doc/_build/html/_static/navigation.png
doc/_build/html/_static/plus.png
doc/_build/html/_static/pygments.css
doc/_build/html/_static/rightsidebar.css
doc/_build/html/_static/searchtools.js
doc/_build/html/_static/sphinxdoc.css
doc/_build/html/_static/stickysidebar.css
doc/_build/html/_static/traditional.css
test/__init__.py
test/test_fileserver.py
test/test_responses.py
test/files/mikeal.png
webenv/__init__.py
webenv/rest.py
webenv.egg-info/PKG-INFO
webenv.egg-info/SOURCES.txt
webenv.egg-info/dependency_links.txt
webenv.egg-info/entry_points.txt
webenv.egg-info/top_level.txt
webenv/applications/__init__.py
webenv/applications/file_server.py