Metadata-Version: 1.0
Name: webenv
Version: 0.6.3
Summary: A thin abstraction layer on top of wsgi providing request, response and application abstractions
Home-page: UNKNOWN
Author: Mikeal Rogers
Author-email: mikeal.rogers@gmail.com
License: MPL 1.1/GPL 2.0/LGPL 2.1
Platform: Any
Classifier: Development Status :: 4 - Beta
Classifier: Environment :: Console
Classifier: Intended Audience :: Developers
Classifier: License :: OSI Approved :: Mozilla Public License 1.1 (MPL 1.1)
Classifier: Operating System :: OS Independent
Classifier: Topic :: Software Development :: Libraries :: Python Modules
